<?xml version="1.0" ?>
<OS_COUNTERS>
	<general_details>
		<used_disk_in_percent>63.7</used_disk_in_percent>
		<used_memory_in_percent>56.5</used_memory_in_percent>
		<current_process_running>212</current_process_running>
		<NumOfOpenedFiles>36216</NumOfOpenedFiles>
		<NumOfThreads>481</NumOfThreads>
		<DiskUsed>11.2714767456</DiskUsed>
	</general_details>
	<NoOfUsersLogged>5</NoOfUsersLogged>
	<UserDetails_1>
		<username>root</username>
		<pid>1714</pid>
		<host>localhost</host>
		<loggedOnAt>1669446400.0</loggedOnAt>
	</UserDetails_1>
	<UserDetails_2>
		<username>root</username>
		<pid>2417</pid>
		<host>localhost</host>
		<loggedOnAt>1669446784.0</loggedOnAt>
	</UserDetails_2>
	<UserDetails_3>
		<username>root</username>
		<pid>2417</pid>
		<host>localhost</host>
		<loggedOnAt>1669462912.0</loggedOnAt>
	</UserDetails_3>
	<UserDetails_4>
		<username>root</username>
		<pid>2417</pid>
		<host>localhost</host>
		<loggedOnAt>1669465728.0</loggedOnAt>
	</UserDetails_4>
	<UserDetails_5>
		<username>root</username>
		<pid>2417</pid>
		<host>localhost</host>
		<loggedOnAt>1669459456.0</loggedOnAt>
	</UserDetails_5>
	<NoOfNetworkInterfaces>4</NoOfNetworkInterfaces>
	<NetInterface_1>
		<NetInterface>lo</NetInterface>
		<bytes_sent>11396</bytes_sent>
		<bytes_recv>11396</bytes_recv>
		<packets_sent>131</packets_sent>
		<packets_recv>131</packets_recv>
		<errin>0</errin>
		<errout>0</errout>
		<dropin>0</dropin>
		<dropout>0</dropout>
	</NetInterface_1>
	<NetInterface_2>
		<NetInterface>virbr0</NetInterface>
		<bytes_sent>0</bytes_sent>
		<bytes_recv>0</bytes_recv>
		<packets_sent>0</packets_sent>
		<packets_recv>0</packets_recv>
		<errin>0</errin>
		<errout>0</errout>
		<dropin>0</dropin>
		<dropout>0</dropout>
	</NetInterface_2>
	<NetInterface_3>
		<NetInterface>virbr0-nic</NetInterface>
		<bytes_sent>0</bytes_sent>
		<bytes_recv>0</bytes_recv>
		<packets_sent>0</packets_sent>
		<packets_recv>0</packets_recv>
		<errin>0</errin>
		<errout>0</errout>
		<dropin>0</dropin>
		<dropout>0</dropout>
	</NetInterface_3>
	<NetInterface_4>
		<NetInterface>ens33</NetInterface>
		<bytes_sent>1498571897</bytes_sent>
		<bytes_recv>747218588</bytes_recv>
		<packets_sent>682574</packets_sent>
		<packets_recv>608359</packets_recv>
		<errin>0</errin>
		<errout>0</errout>
		<dropin>0</dropin>
		<dropout>0</dropout>
	</NetInterface_4>
	<CpuCounters>
		<user>6.06</user>
		<nice>0.05</nice>
		<system>1.40</system>
		<iowait>0.06</iowait>
		<steal>0.00</steal>
		<idle>92.43</idle>
	</CpuCounters>
</OS_COUNTERS>

